[{"id":"18c48935.6a8767","type":"tab","label":"Flow 1","disabled":false,"info":""},{"id":"f12dd4db.3f3ca8","type":"ui_form","z":"18c48935.6a8767","name":"","label":"","group":"12426382.1e18bc","order":0,"width":0,"height":0,"options":[{"label":"Status\t","value":"a","type":"number","required":true,"rows":null},{"label":"Adult Mortality","value":"b","type":"number","required":true,"rows":null},{"label":"infant deaths","value":"c","type":"number","required":true,"rows":null},{"label":"Alcohol","value":"d","type":"number","required":true,"rows":null},{"label":"percentage expenditure","value":"e","type":"number","required":true,"rows":null},{"label":"Hepatitis B","value":"f","type":"number","required":true,"rows":null},{"label":"Measles ","value":"g","type":"number","required":true,"rows":null},{"label":" BMI ","value":"h","type":"number","required":true,"rows":null},{"label":"under-five deaths","value":"i","type":"number","required":true,"rows":null},{"label":"Polio","value":"j","type":"number","required":true,"rows":null},{"label":"Total expenditure","value":"k","type":"number","required":true,"rows":null},{"label":"Diphtheria ","value":"l","type":"number","required":true,"rows":null},{"label":" HIV/AIDS","value":"m","type":"number","required":true,"rows":null},{"label":"GDP","value":"n","type":"number","required":true,"rows":null},{"label":"Population","value":"o","type":"number","required":true,"rows":null},{"label":" thinness  1-19 years","value":"p","type":"number","required":true,"rows":null},{"label":" thinness 5-9 years","value":"q","type":"number","required":true,"rows":null},{"label":"Income composition of resources","value":"r","type":"number","required":true,"rows":null},{"label":"Schooling","value":"s","type":"number","required":true,"rows":null}],"formValue":{"a":"","b":"","c":"","d":"","e":"","f":"","g":"","h":"","i":"","j":"","k":"","l":"","m":"","n":"","o":"","p":"","q":"","r":"","s":""},"payload":"","submit":"submit","cancel":"cancel","topic":"","x":70,"y":100,"wires":[["473bfb1c.556b14"]]},{"id":"473bfb1c.556b14","type":"function","z":"18c48935.6a8767","name":"pre token","func":"//make user given values as global variables\nglobal.set(\"a\",msg.payload.a);\nglobal.set(\"b\",msg.payload.b);\nglobal.set(\"c\",msg.payload.c);\nglobal.set(\"d\",msg.payload.d);\nglobal.set(\"e\",msg.payload.e);\nglobal.set(\"f\",msg.payload.f);\nglobal.set(\"g\",msg.payload.g);\nglobal.set(\"h\",msg.payload.h);\nglobal.set(\"i\",msg.payload.i);\nglobal.set(\"j\",msg.payload.j);\nglobal.set(\"k\",msg.payload.k);\nglobal.set(\"l\",msg.payload.l);\nglobal.set(\"m\",msg.payload.m);\nglobal.set(\"n\",msg.payload.n);\nglobal.set(\"o\",msg.payload.o);\nglobal.set(\"p\",msg.payload.p);\nglobal.set(\"q\",msg.payload.q);\nglobal.set(\"r\",msg.payload.r);\nglobal.set(\"s\",msg.payload.s);\n\n//following are required to receive a token\nvar apikey=\"HB-Z_Z1-p0WtZK7X6QEPRBV4vwxwsiAX99YgqyZPaUog\";\nmsg.headers={\"content-type\":\"application/x-www-form-urlencoded\"};\nmsg.payload={\"grant_type\":\"urn:ibm:params:oauth:grant-type:apikey\",\"apikey\":apikey};\nreturn msg;\n","outputs":1,"noerr":0,"x":220,"y":100,"wires":[["dc7056b2.3989b8"]]},{"id":"4620dbe1.273d94","type":"http request","z":"18c48935.6a8767","name":"","method":"POST","ret":"obj","paytoqs":false,"url":"https://eu-gb.ml.cloud.ibm.com/v3/wml_instances/94d0e4a5-dcbb-4393-a834-4e0a6d7a407c/deployments/a7cd5be6-9a8a-4229-9ba8-c922f72f06e3/online","tls":"","persist":false,"proxy":"","authType":"","x":470,"y":220,"wires":[["39435a32.6e3166","a346ed0.5606f1"]]},{"id":"2ba49e56.53d7c2","type":"debug","z":"18c48935.6a8767","name":"","active":true,"tosidebar":true,"console":false,"tostatus":false,"complete":"payload","targetType":"msg","x":710,"y":440,"wires":[]},{"id":"a346ed0.5606f1","type":"function","z":"18c48935.6a8767","name":"getFrom Endpoint","func":"msg.payload=msg.payload.values[0][0];\nreturn msg;","outputs":1,"noerr":0,"x":390,"y":480,"wires":[["2ba49e56.53d7c2","966213ec.c12a9"]]},{"id":"39435a32.6e3166","type":"debug","z":"18c48935.6a8767","name":"","active":true,"tosidebar":true,"console":false,"tostatus":false,"complete":"payload","targetType":"msg","x":710,"y":140,"wires":[]},{"id":"bc39b31e.e102f","type":"function","z":"18c48935.6a8767","name":"sendTo Endpoint","func":"//get token and make headers\nvar token=msg.payload.access_token;\nvar instance_id=\"94d0e4a5-dcbb-4393-a834-4e0a6d7a407c\"\nmsg.headers={'Content-Type': 'application/json',\"Authorization\":\"Bearer \"+token,\"ML-Instance-ID\":instance_id}\n\n//get variables that are set earlier\nvar a = global.get(\"a\");\nvar b = global.get(\"b\");\nvar c = global.get(\"c\");\nvar d = global.get(\"d\");\nvar e = global.get(\"e\");\nvar f = global.get(\"f\");\nvar g = global.get(\"g\");\nvar h = global.get(\"h\");\nvar i = global.get(\"i\");\nvar j = global.get(\"j\");\nvar k = global.get(\"k\");\nvar l = global.get(\"l\");\nvar m = global.get(\"m\");\nvar n = global.get(\"n\");\nvar o = global.get(\"o\");\nvar p = global.get(\"p\");\nvar q = global.get(\"q\");\nvar r = global.get(\"r\");\nvar s = global.get(\"s\");\n\n\n\n//send the user values to service endpoint\nmsg.payload = \n{\"fields\":[\"status\", \"Adult Mortality\", \"infant deaths\", \"Alcohol\",\n       \"percentage expenditure\", \"Hepatitis B\", \"Measles \", \" BMI \",\n       \"under-five deaths \", \"Polio\", \"Total expenditure\", \"Diphtheria \",\n       \" HIV/AIDS\", \"GDP\", \"Population\", \" thinness  1-19 years\",\n       \" thinness 5-9 years\", \"Income composition of resources\", \"Schooling\"\n       ],\n\"values\":[[a,b,c,d,e,f,g,h,i,j,k,l,m,n,o,p,q,r,s]]};\n\nreturn msg;\n","outputs":1,"noerr":0,"x":210,"y":240,"wires":[["4620dbe1.273d94"]]},{"id":"dc7056b2.3989b8","type":"http request","z":"18c48935.6a8767","name":"","method":"POST","ret":"obj","paytoqs":false,"url":"https://iam.cloud.ibm.com/identity/token","tls":"","persist":false,"proxy":"","authType":"basic","x":370,"y":100,"wires":[["bc39b31e.e102f"]]},{"id":"966213ec.c12a9","type":"ui_text","z":"18c48935.6a8767","group":"12426382.1e18bc","order":1,"width":0,"height":0,"name":"","label":"Prediction","format":"{{msg.payload}}","layout":"row-spread","x":720,"y":660,"wires":[]},{"id":"12426382.1e18bc","type":"ui_group","z":"","name":"Default","tab":"9f8e333a.e5b74","order":1,"disp":true,"width":"6","collapse":false},{"id":"9f8e333a.e5b74","type":"ui_tab","z":"","name":"Home","icon":"dashboard","disabled":false,"hidden":false}]